openbrowser/__init__.py
openbrowser/cli.py
openbrowser/config.py
openbrowser/exceptions.py
openbrowser/init_cmd.py
openbrowser/logging_config.py
openbrowser/observability.py
openbrowser/py.typed
openbrowser/types.py
openbrowser/utils.py
openbrowser/actor/__init__.py
openbrowser/actor/element.py
openbrowser/actor/mouse.py
openbrowser/actor/page.py
openbrowser/actor/utils.py
openbrowser/actor/playground/flights.py
openbrowser/actor/playground/mixed_automation.py
openbrowser/actor/playground/playground.py
openbrowser/agent/gif.py
openbrowser/agent/graph.py
openbrowser/agent/prompts.py
openbrowser/agent/service.py
openbrowser/agent/views.py
openbrowser/agent/message_manager/service.py
openbrowser/agent/message_manager/utils.py
openbrowser/agent/message_manager/views.py
openbrowser/browser/__init__.py
openbrowser/browser/events.py
openbrowser/browser/profile.py
openbrowser/browser/python_highlights.py
openbrowser/browser/session.py
openbrowser/browser/session_manager.py
openbrowser/browser/video_recorder.py
openbrowser/browser/views.py
openbrowser/browser/watchdog_base.py
openbrowser/browser/watchdogs/__init__.py
openbrowser/browser/watchdogs/aboutblank_watchdog.py
openbrowser/browser/watchdogs/crash_watchdog.py
openbrowser/browser/watchdogs/default_action_watchdog.py
openbrowser/browser/watchdogs/dom_watchdog.py
openbrowser/browser/watchdogs/downloads_watchdog.py
openbrowser/browser/watchdogs/local_browser_watchdog.py
openbrowser/browser/watchdogs/permissions_watchdog.py
openbrowser/browser/watchdogs/popups_watchdog.py
openbrowser/browser/watchdogs/recording_watchdog.py
openbrowser/browser/watchdogs/screenshot_watchdog.py
openbrowser/browser/watchdogs/security_watchdog.py
openbrowser/browser/watchdogs/storage_state_watchdog.py
openbrowser/code_use/README.md
openbrowser/code_use/__init__.py
openbrowser/code_use/formatting.py
openbrowser/code_use/namespace.py
openbrowser/code_use/notebook_export.py
openbrowser/code_use/service.py
openbrowser/code_use/utils.py
openbrowser_ai-0.1.12.dist-info/METADATA
openbrowser_ai-0.1.12.dist-info/WHEEL
openbrowser_ai-0.1.12.dist-info/entry_points.txt
openbrowser_ai-0.1.12.dist-info/licenses/LICENSE
openbrowser_ai-0.1.12.dist-info/RECORD
