Metadata-Version: 2.4
Name: openbrowser-ai
Version: 0.1.12
Summary: Agentic browser automation using LangGraph and raw CDP
License-File: LICENSE
Requires-Python: >=3.12
Requires-Dist: aiofiles
Requires-Dist: browser-use==0.9.5
Requires-Dist: bubus>=1.5.6
Requires-Dist: cdp-use
Requires-Dist: click>=8.1.8
Requires-Dist: google-genai>=0.2.0
Requires-Dist: httpx>=0.28.1
Requires-Dist: imageio-ffmpeg>=0.6.0
Requires-Dist: imageio>=2.37.2
Requires-Dist: langchain-core>=0.3.0
Requires-Dist: langchain-openai>=0.2.0
Requires-Dist: langgraph
Requires-Dist: litellm==1.80.0
Requires-Dist: markdownify>=0.11.6
Requires-Dist: numpy>=2.4.0
Requires-Dist: openai<2.0.0,>=1.99.5
Requires-Dist: pandas>=2.2.0
Requires-Dist: pillow>=11.0.0
Requires-Dist: playwright
Requires-Dist: psutil>=7.2.0
Requires-Dist: pydantic-settings>=2.0.0
Requires-Dist: pydantic>=2.0.0
Requires-Dist: python-dotenv
Requires-Dist: rich>=13.0.0
Requires-Dist: websockets>=15.0.1
Provides-Extra: all
Requires-Dist: anthropic>=0.68.0; extra == 'all'
Requires-Dist: boto3; extra == 'all'
Requires-Dist: groq>=0.30.0; extra == 'all'
Requires-Dist: imageio[ffmpeg]; extra == 'all'
Requires-Dist: numpy; extra == 'all'
Requires-Dist: ollama>=0.5.1; extra == 'all'
Requires-Dist: posthog>=3.7.0; extra == 'all'
Requires-Dist: pypdf; extra == 'all'
Requires-Dist: reportlab; extra == 'all'
Requires-Dist: textual>=3.2.0; extra == 'all'
Provides-Extra: anthropic
Requires-Dist: anthropic>=0.68.0; extra == 'anthropic'
Provides-Extra: aws
Requires-Dist: boto3; extra == 'aws'
Provides-Extra: azure
Requires-Dist: openai; extra == 'azure'
Provides-Extra: cli
Requires-Dist: textual>=3.2.0; extra == 'cli'
Provides-Extra: dev
Requires-Dist: pytest-asyncio>=1.0.0; extra == 'dev'
Requires-Dist: pytest-cov>=6.0.0; extra == 'dev'
Requires-Dist: pytest>=9.0.2; extra == 'dev'
Provides-Extra: groq
Requires-Dist: groq>=0.30.0; extra == 'groq'
Provides-Extra: ollama
Requires-Dist: ollama>=0.5.1; extra == 'ollama'
Provides-Extra: pdf
Requires-Dist: pypdf; extra == 'pdf'
Requires-Dist: reportlab; extra == 'pdf'
Provides-Extra: telemetry
Requires-Dist: posthog>=3.7.0; extra == 'telemetry'
Provides-Extra: video
Requires-Dist: imageio[ffmpeg]; extra == 'video'
Requires-Dist: numpy; extra == 'video'
